{
	"SkillInfo": {
		"技能类型": "主动",
		"Index": 4050,
		"技能名称": "真·当阳怒吼",
		"描述": "同时令多个目标进入破甲状态，持续时间10秒，招式使用间隔时间900秒",
		"IconIndex": 1623,
		"职业": 0,
		"伤害": 0,
		"蓝耗": 0,
		"Sk3Id": 0,
		"Ef3Id": 8407,
		"友方为目标群体技能": 0,
		"技能矩形范围距离目标中心横向距离": 0,
		"技能矩形范围距离目标中心纵向距离": 0,
		"技能矩形宽度": 0,
		"技能矩形长度": 0,
		"攻击距离": 230,
		"群攻范围左边界": -150,
		"群攻范围下边界": -50,
		"群攻范围右边界": 300,
		"群攻范围上边界": 100,
		"冷却时间(ms)": 900000,
		"目标僵直时间(ms)": 0,
		"后摇时间(ms)": 700,
		"聚气时间(ms)": 0,
		"攻击段数": 1,
		"等级": 0,
		"释放时显示字幕": "",
		"Sk3FileName": "0000.sk3",
		"Ef3FileName": "8407.ef3",
		"IconFilePath": ".\\res\\UiRes\\Version04\\Icon\\Skill\\1623.gsa"
	},
	"PlayerAction": {},
	"SkillEffect": [
		{
			"Id": 1016,
			"GsoFileName": "Magic1016.gso",
			"Name": "Track1",
			"PlayMode": 0,
			"PlayReserve": 0,
			"Speed": 100,
			"MoveSpeed": 100,
			"Sort": 0,
			"BlendMode": 1,
			"LerpMode": 0,
			"BlurNum": 0,
			"BlurInterval": 100,
			"BlurAlpha": 1.0,
			"BlurScale": 1.0,
			"DirNum": 1,
			"CenterX": 0,
			"CenterY": 0,
			"SubNumber": 0,
			"SubTime": 0,
			"SubRangeX": 0,
			"SubRangeY": 0,
			"TrackType": 0,
			"RenderLv": 0,
			"TrackKeyFrame": [
				{
					"Time": 1105,
					"X": 100.0,
					"Y": -100.0,
					"Z": 0.0,
					"XScale": 1.0,
					"YScale": 1.0,
					"Rotate": 0.0,
					"R": 255.0,
					"G": 255.0,
					"B": 255.0,
					"A": 1.0,
					"Hold": 0
				},
				{
					"Time": 1215,
					"X": 162.0,
					"Y": -100.0,
					"Z": 0.0,
					"XScale": 1.0,
					"YScale": 1.0,
					"Rotate": 0.0,
					"R": 255.0,
					"G": 255.0,
					"B": 255.0,
					"A": 1.0,
					"Hold": 0
				},
				{
					"Time": 1305,
					"X": 200.0,
					"Y": -100.0,
					"Z": 0.0,
					"XScale": 1.0,
					"YScale": 1.0,
					"Rotate": 0.0,
					"R": 255.0,
					"G": 255.0,
					"B": 255.0,
					"A": 0.0,
					"Hold": 0
				}
			],
			"TrackMusic": [],
			"TrackAttack": []
		},
		{
			"Id": 1016,
			"GsoFileName": "Magic1016.gso",
			"Name": "Track1",
			"PlayMode": 0,
			"PlayReserve": 0,
			"Speed": 100,
			"MoveSpeed": 100,
			"Sort": 0,
			"BlendMode": 1,
			"LerpMode": 0,
			"BlurNum": 0,
			"BlurInterval": 100,
			"BlurAlpha": 1.0,
			"BlurScale": 1.0,
			"DirNum": 1,
			"CenterX": 0,
			"CenterY": 0,
			"SubNumber": 0,
			"SubTime": 0,
			"SubRangeX": 0,
			"SubRangeY": 0,
			"TrackType": 0,
			"RenderLv": 0,
			"TrackKeyFrame": [
				{
					"Time": 1155,
					"X": 100.0,
					"Y": -50.0,
					"Z": 0.0,
					"XScale": 1.0,
					"YScale": 1.0,
					"Rotate": 0.0,
					"R": 255.0,
					"G": 255.0,
					"B": 255.0,
					"A": 1.0,
					"Hold": 0
				},
				{
					"Time": 1260,
					"X": 162.0,
					"Y": -50.0,
					"Z": 0.0,
					"XScale": 1.0,
					"YScale": 1.0,
					"Rotate": 0.0,
					"R": 255.0,
					"G": 255.0,
					"B": 255.0,
					"A": 1.0,
					"Hold": 0
				},
				{
					"Time": 1355,
					"X": 200.0,
					"Y": -50.0,
					"Z": 0.0,
					"XScale": 1.0,
					"YScale": 1.0,
					"Rotate": 0.0,
					"R": 255.0,
					"G": 255.0,
					"B": 255.0,
					"A": 0.0,
					"Hold": 0
				}
			],
			"TrackMusic": [],
			"TrackAttack": []
		},
		{
			"Id": 1016,
			"GsoFileName": "Magic1016.gso",
			"Name": "Track1",
			"PlayMode": 0,
			"PlayReserve": 0,
			"Speed": 100,
			"MoveSpeed": 100,
			"Sort": 0,
			"BlendMode": 1,
			"LerpMode": 0,
			"BlurNum": 0,
			"BlurInterval": 100,
			"BlurAlpha": 1.0,
			"BlurScale": 1.0,
			"DirNum": 1,
			"CenterX": 0,
			"CenterY": 0,
			"SubNumber": 0,
			"SubTime": 0,
			"SubRangeX": 0,
			"SubRangeY": 0,
			"TrackType": 0,
			"RenderLv": 0,
			"TrackKeyFrame": [
				{
					"Time": 1200,
					"X": 250.0,
					"Y": -80.0,
					"Z": 0.0,
					"XScale": 1.0,
					"YScale": 1.0,
					"Rotate": 0.0,
					"R": 255.0,
					"G": 255.0,
					"B": 255.0,
					"A": 1.0,
					"Hold": 0
				},
				{
					"Time": 1305,
					"X": 311.0,
					"Y": -80.0,
					"Z": 0.0,
					"XScale": 1.0,
					"YScale": 1.0,
					"Rotate": 0.0,
					"R": 255.0,
					"G": 255.0,
					"B": 255.0,
					"A": 1.0,
					"Hold": 0
				},
				{
					"Time": 1400,
					"X": 350.0,
					"Y": -80.0,
					"Z": 0.0,
					"XScale": 1.0,
					"YScale": 1.0,
					"Rotate": 0.0,
					"R": 255.0,
					"G": 255.0,
					"B": 255.0,
					"A": 0.0,
					"Hold": 0
				}
			],
			"TrackMusic": [
				{
					"Time": 2165,
					"Id": 3013,
					"FilePath": ".\\SNDEFFECT\\3013.wav",
					"Volume": 1.0
				},
				{
					"Time": 2285,
					"Id": 3013,
					"FilePath": ".\\SNDEFFECT\\3013.wav",
					"Volume": 1.0
				}
			],
			"TrackAttack": []
		},
		{
			"Id": 1016,
			"GsoFileName": "Magic1016.gso",
			"Name": "Track1",
			"PlayMode": 0,
			"PlayReserve": 0,
			"Speed": 100,
			"MoveSpeed": 100,
			"Sort": 0,
			"BlendMode": 1,
			"LerpMode": 0,
			"BlurNum": 0,
			"BlurInterval": 100,
			"BlurAlpha": 1.0,
			"BlurScale": 1.0,
			"DirNum": 1,
			"CenterX": 0,
			"CenterY": 0,
			"SubNumber": 0,
			"SubTime": 0,
			"SubRangeX": 0,
			"SubRangeY": 0,
			"TrackType": 0,
			"RenderLv": 0,
			"TrackKeyFrame": [
				{
					"Time": 1105,
					"X": 100.0,
					"Y": -100.0,
					"Z": 0.0,
					"XScale": 1.0,
					"YScale": 1.0,
					"Rotate": 0.0,
					"R": 255.0,
					"G": 255.0,
					"B": 255.0,
					"A": 1.0,
					"Hold": 0
				},
				{
					"Time": 1215,
					"X": 162.0,
					"Y": -100.0,
					"Z": 0.0,
					"XScale": 1.0,
					"YScale": 1.0,
					"Rotate": 0.0,
					"R": 255.0,
					"G": 255.0,
					"B": 255.0,
					"A": 1.0,
					"Hold": 0
				},
				{
					"Time": 1305,
					"X": 200.0,
					"Y": -100.0,
					"Z": 0.0,
					"XScale": 1.0,
					"YScale": 1.0,
					"Rotate": 0.0,
					"R": 255.0,
					"G": 255.0,
					"B": 255.0,
					"A": 0.0,
					"Hold": 0
				}
			],
			"TrackMusic": [],
			"TrackAttack": [
				{
					"Time": 840,
					"value": 100,
					"type": 0
				}
			]
		},
		{
			"Id": 1016,
			"GsoFileName": "Magic1016.gso",
			"Name": "Track1",
			"PlayMode": 0,
			"PlayReserve": 0,
			"Speed": 100,
			"MoveSpeed": 100,
			"Sort": 0,
			"BlendMode": 1,
			"LerpMode": 0,
			"BlurNum": 0,
			"BlurInterval": 100,
			"BlurAlpha": 1.0,
			"BlurScale": 1.0,
			"DirNum": 1,
			"CenterX": 0,
			"CenterY": 0,
			"SubNumber": 0,
			"SubTime": 0,
			"SubRangeX": 0,
			"SubRangeY": 0,
			"TrackType": 0,
			"RenderLv": 0,
			"TrackKeyFrame": [
				{
					"Time": 1155,
					"X": 100.0,
					"Y": -50.0,
					"Z": 0.0,
					"XScale": 1.0,
					"YScale": 1.0,
					"Rotate": 0.0,
					"R": 255.0,
					"G": 255.0,
					"B": 255.0,
					"A": 1.0,
					"Hold": 0
				},
				{
					"Time": 1260,
					"X": 162.0,
					"Y": -50.0,
					"Z": 0.0,
					"XScale": 1.0,
					"YScale": 1.0,
					"Rotate": 0.0,
					"R": 255.0,
					"G": 255.0,
					"B": 255.0,
					"A": 1.0,
					"Hold": 0
				},
				{
					"Time": 1350,
					"X": 200.0,
					"Y": -50.0,
					"Z": 0.0,
					"XScale": 1.0,
					"YScale": 1.0,
					"Rotate": 0.0,
					"R": 255.0,
					"G": 255.0,
					"B": 255.0,
					"A": 0.0,
					"Hold": 0
				}
			],
			"TrackMusic": [],
			"TrackAttack": []
		},
		{
			"Id": 1016,
			"GsoFileName": "Magic1016.gso",
			"Name": "Track1",
			"PlayMode": 0,
			"PlayReserve": 0,
			"Speed": 100,
			"MoveSpeed": 100,
			"Sort": 0,
			"BlendMode": 1,
			"LerpMode": 0,
			"BlurNum": 0,
			"BlurInterval": 100,
			"BlurAlpha": 1.0,
			"BlurScale": 1.0,
			"DirNum": 1,
			"CenterX": 0,
			"CenterY": 0,
			"SubNumber": 0,
			"SubTime": 0,
			"SubRangeX": 0,
			"SubRangeY": 0,
			"TrackType": 0,
			"RenderLv": 0,
			"TrackKeyFrame": [
				{
					"Time": 1200,
					"X": 250.0,
					"Y": -80.0,
					"Z": 0.0,
					"XScale": 1.0,
					"YScale": 1.0,
					"Rotate": 0.0,
					"R": 255.0,
					"G": 255.0,
					"B": 255.0,
					"A": 1.0,
					"Hold": 0
				},
				{
					"Time": 1305,
					"X": 311.0,
					"Y": -80.0,
					"Z": 0.0,
					"XScale": 1.0,
					"YScale": 1.0,
					"Rotate": 0.0,
					"R": 255.0,
					"G": 255.0,
					"B": 255.0,
					"A": 1.0,
					"Hold": 0
				},
				{
					"Time": 1400,
					"X": 350.0,
					"Y": -80.0,
					"Z": 0.0,
					"XScale": 1.0,
					"YScale": 1.0,
					"Rotate": 0.0,
					"R": 255.0,
					"G": 255.0,
					"B": 255.0,
					"A": 0.0,
					"Hold": 0
				}
			],
			"TrackMusic": [],
			"TrackAttack": []
		}
	]
}
